{
  "name": "Arc",
  "description": "Chromium based browser",
  "version": "1.143.2",
  "url": "https://intunebrew.blob.core.windows.net/pkg/arc_1.143.2.pkg",
  "vendor_url": "https://releases.arc.net/release/Arc-1.142.1-78710.zip",
  "bundleId": "company.thebrowser.Browser",
  "homepage": "https://arc.net/",
  "fileName": "arc_1.143.2.pkg",
  "type": "app",
  "sha": "d76abbdb081868cb2d385b4998d378a97d99135924c8dae6848b586fae618389",
  "previous_version": "1.143.2",
  "qa_info": {
    "qa_timestamp": "2025-05-16T13:19:57Z",
    "qa_result": "Installation successful and verified",
    "download_status": "success",
    "sha_status": "verified",
    "install_status": "success",
    "verify_status": "app_found",
    "bundle_id_status": "verified",
    "installed_version": "1.95.0"
  },
  "category": "Browsers",
  "publisher": "The Browser Company, LLC"
}
