{
  "name": "Beeper",
  "description": "Universal chat app powered by Matrix",
  "version": "4.2.367",
  "url": "https://intunebrew.blob.core.windows.net/pkg/beeper_4.2.367.pkg",
  "bundleId": "im.beeper",
  "homepage": "https://www.beeper.com/",
  "fileName": "beeper_4.2.367.pkg",
  "type": "app",
  "sha": "d36daa0a7568adc8d7c4327553e2afaf3d2e216a38ac9c937ed526da45dfa0ff",
  "previous_version": "4.2.367",
  "qa_info": {
    "qa_timestamp": "2025-05-16T13:21:44Z",
    "qa_result": "Installation successful and verified",
    "download_status": "success",
    "sha_status": "verified",
    "install_status": "success",
    "verify_status": "app_found",
    "bundle_id_status": "mismatch",
    "installed_version": "4.0.693"
  }
}
