{
  "name": "Bitfocus Companion",
  "description": "Streamdeck extension and emulation software",
  "version": "5.0.2",
  "url": "https://cf-pub.bitfocus.io/companion/companion/companion-mac-arm64-5.0.2-9665-stable-5eb89669c6.dmg",
  "vendor_url": "https://s4.bitfocus.io/builds/companion/companion-mac-arm64-4.2.6+8823-stable-4ecdfe70ba.dmg",
  "bundleId": "companion.bitfocus.no",
  "homepage": "https://bitfocus.io/companion",
  "homebrew_cask": "companion",
  "fileName": "companion-mac-arm64-5.0.2-9665-stable-5eb89669c6.dmg",
  "sha": "906f1bcfb352640fe694f04326550efb28642109f66e5a13a42cef511ca15ca5",
  "category": "Utilities",
  "publisher": "Bitfocus",
  "previous_version": "5.0.1"
}