{
  "name": "Bria",
  "description": "Softphone application",
  "version": "6.8.7",
  "url": "https://counterpath.s3.amazonaws.com/downloads/Bria_6.8.7_130266.dmg",
  "vendor_url": "https://counterpath.s3.amazonaws.com/downloads/Bria_6.8.6_129508.dmg",
  "bundleId": "com.CounterPath_Corporation.Bria",
  "homepage": "https://www.counterpath.com/bria-solo/",
  "fileName": "Bria_6.8.7_130266.dmg",
  "sha": "7859ef30105bfe1a629c889c354eae1f83bcbf2f7e3f579d7fbb0aab71fd722a",
  "category": "Communication",
  "publisher": "CounterPath Corporation",
  "previous_version": "6.8.6"
}