{
  "name": "BusyContacts",
  "description": "Contact manager focusing on efficiency",
  "version": "2025.4.3",
  "url": "https://intunebrew.blob.core.windows.net/pkg/busycontacts_2025.4.3.pkg",
  "bundleId": "com.busymac.busycontacts.pkg",
  "homepage": "https://www.busymac.com/busycontacts/index.html",
  "fileName": "busycontacts_2025.4.3.pkg",
  "type": "app",
  "sha": "49ee087e675e618a5e90c82af846181d3ca56f29505869630f9f4b55cd998ea8",
  "changelog": "https://www.busymac.com/busycontacts/releasenotes.html",
  "previous_version": "2025.4.3",
  "qa_info": {
    "qa_timestamp": "2025-05-12T11:45:36Z",
    "qa_result": "Installation successful and verified",
    "download_status": "success",
    "sha_status": "verified",
    "install_status": "success",
    "verify_status": "app_found",
    "bundle_id_status": "mismatch",
    "installed_version": "2025.2.1"
  }
}
