{
  "name": "CleanMyMac",
  "description": "Tool to remove unnecessary files and folders from disk",
  "version": "5.2.8",
  "url": "https://intunebrew.blob.core.windows.net/pkg/cleanmymac_5.2.8.pkg",
  "bundleId": "com.macpaw.CleanMyMac5.HealthMonitor",
  "homepage": "https://macpaw.com/cleanmymac",
  "fileName": "cleanmymac_5.2.8.pkg",
  "type": "app",
  "sha": "9abb061edc1186115842e08d637e74f90a860c61a6cd0433715581a3d2e4adca",
  "changelog": "https://macpaw.com/support/cleanmymac/knowledgebase/cleanmymac-x-release-notes",
  "previous_version": "5.2.8",
  "qa_info": {
    "qa_timestamp": "2025-05-14T06:44:22Z",
    "qa_result": "Installation successful and verified",
    "download_status": "success",
    "sha_status": "verified",
    "install_status": "success",
    "verify_status": "app_found",
    "bundle_id_status": "mismatch",
    "installed_version": "5.0.9"
  }
}
