{
  "name": "CotEditor",
  "description": "Plain-text editor for web pages, program source codes and more",
  "version": "6.0.0",
  "url": "https://github.com/coteditor/CotEditor/releases/download/6.0.0/CotEditor_6.0.0.dmg",
  "bundleId": "com.coteditor.CotEditor",
  "homepage": "https://coteditor.com/",
  "fileName": "CotEditor_6.0.0.dmg",
  "sha": "38c1a38d78fb4cd666107bf286ad27fb1cf413ed21881e756ccfc875f9312de4",
  "qa_info": {
    "qa_timestamp": "2025-05-12T11:49:51Z",
    "qa_result": "Installation successful and verified",
    "download_status": "success",
    "sha_status": "verified",
    "install_status": "success",
    "verify_status": "app_found",
    "bundle_id_status": "verified",
    "installed_version": "5.1.6"
  },
  "previous_version": "5.2.3"
}