{
  "name": "Cryptomator",
  "description": "Multi-platform client-side cloud file encryption tool",
  "version": "1.19.1",
  "url": "https://github.com/cryptomator/cryptomator/releases/download/1.19.1/Cryptomator-1.19.1-arm64.dmg",
  "bundleId": "org.cryptomator",
  "homepage": "https://cryptomator.org/",
  "fileName": "Cryptomator-1.19.1-arm64.dmg",
  "sha": "c208184d36b1570e00c2929b3b230679191235742385e883863135ee67e9c581",
  "qa_info": {
    "qa_timestamp": "2025-05-16T13:27:25Z",
    "qa_result": "Installation successful and verified",
    "download_status": "success",
    "sha_status": "verified",
    "install_status": "success",
    "verify_status": "app_found",
    "bundle_id_status": "verified",
    "installed_version": "1.16.2"
  },
  "category": "Security",
  "publisher": "The Cryptomator Project",
  "previous_version": "1.19.1"
}