{
  "name": "DockDoor",
  "description": "Window peeking utility app",
  "version": "1.39.3",
  "url": "https://github.com/ejbills/DockDoor/releases/download/1.39.3/DockDoor.dmg",
  "vendor_url": "https://github.com/ejbills/DockDoor/releases/download/1.34.1/DockDoor.dmg",
  "bundleId": "com.ejbills.DockDoor",
  "homepage": "https://dockdoor.net/",
  "fileName": "DockDoor.dmg",
  "sha": "fe28259b978df36af8c95099e5b875d40adcea3dd4179f3cc2b67cbd2ac86ab4",
  "qa_info": {
    "qa_timestamp": "2025-05-12T12:26:40Z",
    "qa_result": "Installation successful and verified",
    "download_status": "success",
    "sha_status": "verified",
    "install_status": "success",
    "verify_status": "app_found",
    "bundle_id_status": "verified",
    "installed_version": "1.9.1"
  },
  "category": "Utilities",
  "publisher": "Unknown",
  "previous_version": "1.39.3"
}