{
  "name": "DockDoor",
  "description": "Window peeking utility app",
  "version": "1.36",
  "url": "https://github.com/ejbills/DockDoor/releases/download/1.36/DockDoor.dmg",
  "vendor_url": "https://github.com/ejbills/DockDoor/releases/download/1.34.1/DockDoor.dmg",
  "bundleId": "com.ejbills.DockDoor",
  "homepage": "https://dockdoor.net/",
  "fileName": "DockDoor.dmg",
  "sha": "ae80a49215d8dbc95842a39642e9ba7058b112145d2dee5b0173a8c9943f8c9f",
  "qa_info": {
    "qa_timestamp": "2025-05-12T12:26:40Z",
    "qa_result": "Installation successful and verified",
    "download_status": "success",
    "sha_status": "verified",
    "install_status": "success",
    "verify_status": "app_found",
    "bundle_id_status": "verified",
    "installed_version": "1.9.1"
  },
  "category": "Utilities",
  "publisher": "Unknown",
  "previous_version": "1.36"
}