{
  "name": "Ecamm Live",
  "description": "Live streaming & video production studio",
  "version": "4.5.8",
  "url": "https://intunebrew.blob.core.windows.net/pkg/ecamm_live_4.5.8.pkg",
  "vendor_url": "https://downloads.ecamm.com/EcammLive.zip",
  "bundleId": "com.ecamm.EcammLive",
  "homepage": "https://www.ecamm.com/",
  "fileName": "ecamm_live_4.5.8.pkg",
  "type": "app",
  "sha": "03ed690b5b3b7ddd6f7c7b4a3036bfbc7ba0a66942559f616a90ee92f4f54f3f",
  "category": "Media",
  "publisher": "Ecamm Network, LLC",
  "previous_version": "4.5.8"
}
