{
  "name": "Jabra Direct",
  "description": "Optimise and personalise your Jabra headset",
  "version": "6.24.20901",
  "url": "https://intunebrew.blob.core.windows.net/pkg/jabra_direct_6.24.20901.pkg",
  "bundleId": "com.jabra.directonline",
  "homepage": "https://www.jabra.com/software-and-services/jabra-direct",
  "fileName": "jabra_direct_6.24.20901.pkg",
  "type": "pkg_in_dmg",
  "changelog": "https://www.jabra.com/support/release-notes/release-note-jabra-direct",
  "sha": "db01c0df0d53d6729b189239d8257c6526af09c21aef020a0d0344f4f9ae45f2",
  "previous_version": "6.23.16101"
}
