{
  "name": "Jellyfin",
  "description": "Media system",
  "version": "10.11.10",
  "url": "https://repo.jellyfin.org/files/server/macos/stable/v10.11.10/arm64/jellyfin_10.11.10-arm64.dmg",
  "vendor_url": "https://repo.jellyfin.org/files/server/macos/stable/v10.11.8/arm64/jellyfin_10.11.8-arm64.dmg",
  "bundleId": "org.jellyfin.JellyfinServer",
  "homepage": "https://jellyfin.org/",
  "fileName": "jellyfin_10.11.10-arm64.dmg",
  "sha": "7ea6013b610885a25f2fc7ab9aa3083cb23939016877e49ad40e29bdb5109932",
  "changelog": "https://github.com/jellyfin/jellyfin/releases",
  "category": "Media",
  "publisher": "The Jellyfin Project",
  "previous_version": "10.11.10"
}