{
  "name": "Krita",
  "description": "Free and open-source painting and sketching program",
  "version": "5.2.15",
  "url": "https://download.kde.org/stable/krita/5.2.15/krita-5.2.15_signed.dmg",
  "bundleId": "org.krita",
  "homepage": "https://krita.org/",
  "fileName": "krita-5.2.15_signed.dmg",
  "sha": "4701cdf74502af763fdfd7f01d94b590f64d8987b9131b4774352734aeed89ac",
  "changelog": "https://krita.org/en/krita-5-2-release-notes/",
  "category": "Design",
  "publisher": "The Krita Foundation",
  "previous_version": "5.2.15"
}