{
  "name": "Multipass",
  "description": "Orchestrates virtual Ubuntu instances",
  "version": "1.16.3",
  "url": "https://github.com/canonical/multipass/releases/download/v1.16.3/multipass-1.16.3+mac-Darwin.pkg",
  "vendor_url": "https://github.com/canonical/multipass/releases/download/v1.16.1/multipass-1.16.1+mac-Darwin.pkg",
  "bundleId": "com.canonical.multipassgui",
  "homepage": "https://github.com/canonical/multipass/",
  "fileName": "multipass-1.16.3+mac-Darwin.pkg",
  "type": "pkg",
  "sha": "7d6eab39614139884cfb5a4aeb68f9b25334356c142d5d4b1f74acdd76082c18",
  "category": "Developer Tools",
  "publisher": "Canonical Ltd.",
  "previous_version": "1.16.2"
}