{
  "name": "OBS",
  "description": "Open-source software for live streaming and screen recording",
  "version": "32.1.2",
  "url": "https://cdn-fastly.obsproject.com/downloads/obs-studio-32.1.2-macos-apple.dmg",
  "vendor_url": "https://cdn-fastly.obsproject.com/downloads/obs-studio-32.1.1-macos-apple.dmg",
  "bundleId": "com.obsproject.obs-studio",
  "homepage": "https://obsproject.com/",
  "fileName": "obs-studio-32.1.2-macos-apple.dmg",
  "sha": "2aeb3aaa99544fefd557f10ac6550e73df71540dd57528b2a1e6f39a55ebacfb",
  "changelog": "https://github.com/obsproject/obs-studio/releases",
  "category": "Media",
  "publisher": "OBS Project",
  "previous_version": "32.1.1"
}