{
  "name": "Opera",
  "description": "Web browser",
  "version": "129.0.5823.65",
  "url": "https://get.geo.opera.com/pub/opera/desktop/129.0.5823.65/mac/Opera_129.0.5823.65_Setup.dmg",
  "bundleId": "com.operasoftware.Opera",
  "homepage": "https://www.opera.com/",
  "fileName": "Opera_129.0.5823.65_Setup.dmg",
  "sha": "ab3a78a131f3ded87e7501153f83107d97c592d312d23cfe6b30a0b4abbcb57d",
  "changelog": "https://blogs.opera.com/desktop/",
  "category": "Browsers",
  "publisher": "Opera Software AS",
  "previous_version": "129.0.5823.44"
}