{
  "name": "Opera",
  "description": "Web browser",
  "version": "133.0.5932.60",
  "url": "https://get.geo.opera.com/pub/opera/desktop/133.0.5932.60/mac/Opera_133.0.5932.60_Setup.dmg",
  "vendor_url": "https://get.geo.opera.com/pub/opera/desktop/130.0.5847.12/mac/Opera_130.0.5847.12_Setup.dmg",
  "bundleId": "com.operasoftware.Opera",
  "homepage": "https://www.opera.com/",
  "homebrew_cask": "opera",
  "fileName": "Opera_133.0.5932.60_Setup.dmg",
  "sha": "e558618917376eedde960022154893a14e7abae2aab04846135c4c508f6b1470",
  "changelog": "https://blogs.opera.com/desktop/",
  "category": "Browsers",
  "publisher": "Opera Software AS",
  "previous_version": "133.0.5932.34"
}