{
  "name": "Paste",
  "description": "Limitless clipboard",
  "version": "6.6.2",
  "url": "https://intunebrew.blob.core.windows.net/pkg/paste_6.6.2.pkg",
  "vendor_url": "https://downloads.pasteapp.io/dist/stable/Paste-6.4.0.zip",
  "bundleId": "com.wiheads.paste-direct",
  "homepage": "https://pasteapp.io/",
  "fileName": "paste_6.6.2.pkg",
  "type": "app",
  "previous_version": "6.6.2",
  "sha": "e02d6b947100b487dc8bfbc8f0b9d7ab031cd11190fed9c0c7492570c059cff9",
  "category": "Productivity",
  "publisher": "Paste"
}
