{
  "name": "Screenflick",
  "description": "Screen recorder with audio",
  "version": "3.3.2",
  "url": "https://intunebrew.blob.core.windows.net/pkg/screenflick_3.3.2.pkg",
  "bundleId": "com.araeliumgroup.screenflick",
  "homepage": "https://www.araelium.com/screenflick-mac-screen-recorder",
  "fileName": "screenflick_3.3.2.pkg",
  "type": "app",
  "sha": "36c5d909f006e7441373ee0752a893550049c846528f91dd3690fff87ee296e2",
  "category": "Media",
  "publisher": "Araelium",
  "previous_version": "3.3.2"
}
