{
  "name": "Sequel Ace",
  "description": "MySQL/MariaDB database management",
  "version": "5.3.0",
  "url": "https://intunebrew.blob.core.windows.net/pkg/sequel_ace_5.3.0.pkg",
  "vendor_url": "https://github.com/Sequel-Ace/Sequel-Ace/releases/download/production/5.2.0-20099/Sequel-Ace-5.2.0.zip",
  "bundleId": "com.sequel-ace.sequel-ace",
  "homepage": "https://github.com/Sequel-Ace/Sequel-Ace",
  "fileName": "sequel_ace_5.3.0.pkg",
  "type": "app",
  "sha": "29f7ac75df10bb31213c04556448c1fecd24249fe0bbf9318595331f22712d7c",
  "previous_version": "5.2.1",
  "category": "Developer Tools",
  "publisher": "Sequel Ace"
}
