{
  "name": "Stats",
  "description": "System monitor for the menu bar",
  "version": "2.12.3",
  "url": "https://github.com/exelban/stats/releases/download/v2.12.3/Stats.dmg",
  "bundleId": "eu.exelban.Stats",
  "homepage": "https://github.com/exelban/stats",
  "fileName": "Stats.dmg",
  "sha": "67d2fddc8c1ef577076e22ab59522b7eac0cb1fbfcb51f371dd7e5f944e3f988",
  "changelog": "https://github.com/exelban/stats/releases",
  "category": "Utilities",
  "publisher": "exelban",
  "previous_version": "2.12.1"
}