{
  "name": "TimeScribe",
  "description": "Working time tracker",
  "version": "1.15.0",
  "url": "https://intunebrew.blob.core.windows.net/pkg/timescribe_1.15.0.pkg",
  "vendor_url": "https://github.com/WINBIGFOX/TimeScribe/releases/download/v1.12.0/TimeScribe-1.12.0-arm64.zip",
  "bundleId": "com.apple.TimeScribe",
  "homepage": "https://timescribe.app/",
  "fileName": "timescribe_1.15.0.pkg",
  "type": "app",
  "sha": "d03ef3f74a0c2dbb41dda872761ad074f9d73e80c93362fd7a0ecfa1bb01db3d",
  "category": "Productivity",
  "publisher": "TimeScribe",
  "previous_version": "1.15.0",
  "homebrew_cask": "timescribe"
}
