{
  "name": "WebCatalog",
  "description": "Tool to run web apps like desktop apps",
  "version": "75.0.2",
  "url": "https://cdn-2.webcatalog.io/webcatalog/WebCatalog-75.0.2-universal.dmg",
  "vendor_url": "https://cdn-2.webcatalog.io/webcatalog/WebCatalog-74.0.2-universal.dmg",
  "bundleId": "com.webcatalog.jordan",
  "homepage": "https://webcatalog.io/",
  "fileName": "WebCatalog-75.0.2-universal.dmg",
  "sha": "377109efce5ebc5c3c764cd60721e1ec237573c1ae7030653348edfaada7e3cc",
  "category": "Productivity",
  "publisher": "WebCatalog",
  "previous_version": "75.0.2"
}