{
  "name": "Windsurf",
  "description": "Agentic IDE powered by AI Flow paradigm",
  "version": "1.12.11",
  "url": "https://windsurf-stable.codeiumdata.com/darwin-arm64-dmg/stable/869df67af2a3134ce6fe3d8395ac0ae23726fd02/Windsurf-darwin-arm64-1.12.11.dmg",
  "bundleId": "com.exafunction.windsurf",
  "homepage": "https://www.codeium.com/windsurf",
  "fileName": "Windsurf-darwin-arm64-1.12.11.dmg",
  "sha": "5b6e99fc6a103e1400646e375c390d65123f585b835971478041cef55d366a9a",
  "changelog": "https://www.codeium.com/windsurf/changelog",
  "previous_version": "1.12.9"
}